you_get/__init__.py
you_get/__main__.py
you_get/common.py
you_get/extractor.py
you_get/json_output.py
you_get/version.py
you_get/cli_wrapper/__init__.py
you_get/cli_wrapper/downloader/__init__.py
you_get/cli_wrapper/openssl/__init__.py
you_get/cli_wrapper/player/__init__.py
you_get/cli_wrapper/player/__main__.py
you_get/cli_wrapper/player/dragonplayer.py
you_get/cli_wrapper/player/gnome_mplayer.py
you_get/cli_wrapper/player/mplayer.py
you_get/cli_wrapper/player/vlc.py
you_get/cli_wrapper/player/wmp.py
you_get/cli_wrapper/transcoder/__init__.py
you_get/cli_wrapper/transcoder/ffmpeg.py
you_get/cli_wrapper/transcoder/libav.py
you_get/cli_wrapper/transcoder/mencoder.py
you_get/extractors/__init__.py
you_get/extractors/acfun.py
you_get/extractors/alive.py
you_get/extractors/archive.py
you_get/extractors/baidu.py
you_get/extractors/bandcamp.py
you_get/extractors/baomihua.py
you_get/extractors/bigthink.py
you_get/extractors/bilibili.py
you_get/extractors/bokecc.py
you_get/extractors/cbs.py
you_get/extractors/ckplayer.py
you_get/extractors/cntv.py
you_get/extractors/coub.py
you_get/extractors/dailymotion.py
you_get/extractors/douban.py
you_get/extractors/douyin.py
you_get/extractors/douyutv.py
you_get/extractors/ehow.py
you_get/extractors/embed.py
you_get/extractors/facebook.py
you_get/extractors/fc2video.py
you_get/extractors/flickr.py
you_get/extractors/freesound.py
you_get/extractors/funshion.py
you_get/extractors/giphy.py
you_get/extractors/google.py
you_get/extractors/heavymusic.py
you_get/extractors/huomaotv.py
you_get/extractors/icourses.py
you_get/extractors/ifeng.py
you_get/extractors/imgur.py
you_get/extractors/infoq.py
you_get/extractors/instagram.py
you_get/extractors/interest.py
you_get/extractors/iqilu.py
you_get/extractors/iqiyi.py
you_get/extractors/iwara.py
you_get/extractors/ixigua.py
you_get/extractors/joy.py
you_get/extractors/kakao.py
you_get/extractors/khan.py
you_get/extractors/ku6.py
you_get/extractors/kuaishou.py
you_get/extractors/kugou.py
you_get-0.4.1730.dist-info/LICENSE.txt
you_get-0.4.1730.dist-info/METADATA
you_get-0.4.1730.dist-info/WHEEL
you_get-0.4.1730.dist-info/entry_points.txt
you_get-0.4.1730.dist-info/top_level.txt
you_get-0.4.1730.dist-info/zip-safe
you_get-0.4.1730.dist-info/RECORD
